ottos_oranges/__init__.py
ottos_oranges/lib/seed.py
ottos_oranges/lib/synthetic.py
ottos_oranges/lib/transform.py
ottos_oranges/ui/cli.py
ottos_oranges/ui/gui.py
ottos_oranges-0.0.1.dist-info/METADATA
ottos_oranges-0.0.1.dist-info/WHEEL
ottos_oranges-0.0.1.dist-info/entry_points.txt
ottos_oranges-0.0.1.dist-info/RECORD
