Metadata-Version: 2.4
Name: ottos-oranges
Version: 0.0.1
Summary: Otto's Oranges
Project-URL: Homepage, https://github.com/ascend-io/ascend-community
Project-URL: Bug Tracker, https://github.com/ascend-io/ascend-community/issues
Author-email: Ascend <hello@ascend.io>
Classifier: License :: OSI Approved :: MIT License
Classifier: Operating System :: OS Independent
Classifier: Programming Language :: Python :: 3
Requires-Python: >=3.12
Requires-Dist: faker
Requires-Dist: ibis-framework[bigquery,datafusion,deltalake,duckdb,polars,snowflake,sqlite]
Requires-Dist: plotly
Requires-Dist: pydantic-ai
Requires-Dist: python-dotenv
Requires-Dist: rich
Requires-Dist: shiny
Requires-Dist: shinyswatch
Requires-Dist: shinywidgets
Requires-Dist: typer
Provides-Extra: dev
Requires-Dist: ipykernel; extra == 'dev'
Requires-Dist: ipython; extra == 'dev'
Requires-Dist: jupyter; extra == 'dev'
Requires-Dist: nbclient; extra == 'dev'
Requires-Dist: ruff; extra == 'dev'
Provides-Extra: test
Requires-Dist: pytest; extra == 'test'
